apsig/__init__.py
apsig/_version.py
apsig/exceptions.py
apsig/ld_signature.py
apsig/rfc9421.py
apsig/tools.py
apsig/actor/keytools.py
apsig/draft/__init__.py
apsig/draft/sign.py
apsig/draft/tools.py
apsig/draft/verify.py
apsig/proof/__init__.py
apsig/proof/sign.py
apsig/proof/verify.py
apsig-0.6.0.dist-info/METADATA
apsig-0.6.0.dist-info/WHEEL
apsig-0.6.0.dist-info/licenses/COPYING.md
apsig-0.6.0.dist-info/licenses/LICENSE
apsig-0.6.0.dist-info/RECORD
