Metadata-Version: 2.4
Name: apsig
Version: 0.6.0
Summary: apsig is collection of signature implemention used in ActivityPub.
Project-URL: Repository, https://github.com/fedi-libs/apsig
Project-URL: Issues, https://github.com/fedi-libs/apsig/issues
Project-URL: Changelog, https://github.com/fedi-libs/apsig/blob/main/CHANGELOG.md
Author-email: AmaseCocoa <cocoa@amase.cc>
License: MIT
License-File: COPYING.md
License-File: LICENSE
Classifier: Development Status :: 4 - Beta
Classifier: Intended Audience :: Developers
Classifier: License :: OSI Approved :: MIT License
Classifier: Natural Language :: English
Classifier: Operating System :: OS Independent
Classifier: Programming Language :: Python :: 3
Classifier: Programming Language :: Python :: 3.10
Classifier: Programming Language :: Python :: 3.11
Classifier: Programming Language :: Python :: 3.12
Classifier: Programming Language :: Python :: 3.13
Classifier: Programming Language :: Python :: 3.14
Classifier: Topic :: Security
Classifier: Topic :: Software Development :: Libraries :: Python Modules
Requires-Python: >=3.10
Requires-Dist: authlib>=1.6.0
Requires-Dist: cryptography>=43.0.1
Requires-Dist: http-sf>=1.0.3
Requires-Dist: jcs>=0.2.1
Requires-Dist: multiformats>=0.3.1.post4
Requires-Dist: pyld[aiohttp,requests]>=2.0.4
Requires-Dist: pytz>=2025.1
Requires-Dist: typing-extensions>=4.12.2
